[{"acRate": 78.3098880889028, "difficulty": "Easy", "freqBar": 0.0, "frontendQuestionId": "1475", "isFavor": false, "paidOnly": false, "status": null, "title": "Final Prices With a Special Discount in a Shop", "titleSlug": "final-prices-with-a-special-discount-in-a-shop", "topicTags": [{"name": "Array", "id": "VG9waWNUYWdOb2RlOjU=", "slug": "array"}, {"name": "Stack", "id": "VG9waWNUYWdOb2RlOjE1", "slug": "stack"}, {"name": "Monotonic Stack", "id": "VG9waWNUYWdOb2RlOjYxMDU0", "slug": "monotonic-stack"}], "hasSolution": false, "hasVideoSolution": false}, {"acRate": 49.82430876817811, "difficulty": "Medium", "freqBar": 100.0, "frontendQuestionId": "1642", "isFavor": false, "paidOnly": false, "status": null, "title": "Furthest Building You Can Reach", "titleSlug": "furthest-building-you-can-reach", "topicTags": [{"name": "Array", "id": "VG9waWNUYWdOb2RlOjU=", "slug": "array"}, {"name": "Greedy", "id": "VG9waWNUYWdOb2RlOjE3", "slug": "greedy"}, {"name": "Heap (Priority Queue)", "id": "VG9waWNUYWdOb2RlOjYxMDUw", "slug": "heap-priority-queue"}], "hasSolution": true, "hasVideoSolution": false}]